{
  "data": [
    {
      "name": "AAA",
      "vol": "377,50"
    },
    {
      "name": "AAM",
      "vol": "30"
    },
    {
      "name": "AAT",
      "vol": "41,30"
    },
    {
      "name": "ABS",
      "vol": "50,60"
    },
    {
      "name": "ABT",
      "vol": ""
    },
    {
      "name": "ACB",
      "vol": "591,90"
    },
    {
      "name": "ACC",
      "vol": "5,50"
    },
    {
      "name": "ACL",
      "vol": "23,30"
    },
    {
      "name": "ADG",
      "vol": "26,30"
    },
    {
      "name": "ADS",
      "vol": "64,30"
    },
    {
      "name": "AGG",
      "vol": "79,20"
    },
    {
      "name": "AGM",
      "vol": "14,70"
    },
    {
      "name": "AGR",
      "vol": "558,10"
    },
    {
      "name": "AMD",
      "vol": "283,50"
    },
    {
      "name": "ANV",
      "vol": "31,00"
    },
    {
      "name": "APC",
      "vol": ""
    },
    {
      "name": "APG",
      "vol": "2,247,00"
    },
    {
      "name": "APH",
      "vol": "426,90"
    },
    {
      "name": "ASM",
      "vol": "1,010,70"
    },
    {
      "name": "ASP",
      "vol": "235,70"
    },
    {
      "name": "AST",
      "vol": ""
    },
    {
      "name": "BBC",
      "vol": "10"
    },
    {
      "name": "BCE",
      "vol": "36,50"
    },
    {
      "name": "BCG",
      "vol": "371,60"
    },
    {
      "name": "BCM",
      "vol": "3,10"
    },
    {
      "name": "BFC",
      "vol": "151,90"
    },
    {
      "name": "BHN",
      "vol": ""
    },
    {
      "name": "BIC",
      "vol": "3,40"
    },
    {
      "name": "BID",
      "vol": "101,20"
    },
    {
      "name": "BKG",
      "vol": "60,70"
    },
    {
      "name": "BMC",
      "vol": "53,90"
    },
    {
      "name": "BMI",
      "vol": "32,20"
    },
    {
      "name": "BMP",
      "vol": "8,00"
    },
    {
      "name": "BRC",
      "vol": "50"
    },
    {
      "name": "BSI",
      "vol": "162,10"
    },
    {
      "name": "BTP",
      "vol": "1,90"
    },
    {
      "name": "BTT",
      "vol": ""
    },
    {
      "name": "BVH",
      "vol": "81,30"
    },
    {
      "name": "BWE",
      "vol": "10,50"
    },
    {
      "name": "C32",
      "vol": "21,40"
    },
    {
      "name": "C47",
      "vol": "57,30"
    },
    {
      "name": "CAV",
      "vol": ""
    },
    {
      "name": "CCI",
      "vol": ""
    },
    {
      "name": "CCL",
      "vol": "34,90"
    },
    {
      "name": "CDC",
      "vol": ""
    },
    {
      "name": "CEE",
      "vol": "30"
    },
    {
      "name": "CFPT2102",
      "vol": "20"
    },
    {
      "name": "CFPT2103",
      "vol": "53,60"
    },
    {
      "name": "CFPT2104",
      "vol": "2,90"
    },
    {
      "name": "CFPT2105",
      "vol": "6,40"
    },
    {
      "name": "CHDB2101",
      "vol": "76,20"
    },
    {
      "name": "CHDB2102",
      "vol": "9,20"
    },
    {
      "name": "CHP",
      "vol": ""
    },
    {
      "name": "CHPG2101",
      "vol": "20,70"
    },
    {
      "name": "CHPG2109",
      "vol": "2,20"
    },
    {
      "name": "CHPG2110",
      "vol": "213,30"
    },
    {
      "name": "CHPG2111",
      "vol": "294,60"
    },
    {
      "name": "CIG",
      "vol": "8,90"
    },
    {
      "name": "CII",
      "vol": "406,00"
    },
    {
      "name": "CKDH2101",
      "vol": "58,10"
    },
    {
      "name": "CKDH2103",
      "vol": "86,50"
    },
    {
      "name": "CKDH2104",
      "vol": "284,30"
    },
    {
      "name": "CKG",
      "vol": "82,60"
    },
    {
      "name": "CLC",
      "vol": "70"
    },
    {
      "name": "CLL",
      "vol": "3,90"
    },
    {
      "name": "CLW",
      "vol": ""
    },
    {
      "name": "CMBB2103",
      "vol": "71,90"
    },
    {
      "name": "CMBB2104",
      "vol": "297,10"
    },
    {
      "name": "CMG",
      "vol": "7,10"
    },
    {
      "name": "CMSN2101",
      "vol": "27,00"
    },
    {
      "name": "CMSN2102",
      "vol": "20,30"
    },
    {
      "name": "CMSN2104",
      "vol": "10"
    },
    {
      "name": "CMSN2105",
      "vol": "90,60"
    },
    {
      "name": "CMSN2106",
      "vol": "15,20"
    },
    {
      "name": "CMV",
      "vol": ""
    },
    {
      "name": "CMWG2104",
      "vol": "26,30"
    },
    {
      "name": "CMWG2106",
      "vol": "56,70"
    },
    {
      "name": "CMWG2107",
      "vol": "182,80"
    },
    {
      "name": "CMX",
      "vol": "89,40"
    },
    {
      "name": "CNG",
      "vol": "200,30"
    },
    {
      "name": "CNVL2101",
      "vol": "21,10"
    },
    {
      "name": "CNVL2102",
      "vol": "81,70"
    },
    {
      "name": "CNVL2103",
      "vol": "111,60"
    },
    {
      "name": "COM",
      "vol": ""
    },
    {
      "name": "CPDR2102",
      "vol": "50"
    },
    {
      "name": "CPNJ2104",
      "vol": "8,70"
    },
    {
      "name": "CPNJ2105",
      "vol": "83,20"
    },
    {
      "name": "CRC",
      "vol": "77,40"
    },
    {
      "name": "CRE",
      "vol": "261,80"
    },
    {
      "name": "CSBT2101",
      "vol": "12,30"
    },
    {
      "name": "CSM",
      "vol": "10"
    },
    {
      "name": "CSTB2101",
      "vol": "60"
    },
    {
      "name": "CSTB2105",
      "vol": "6,20"
    },
    {
      "name": "CSTB2106",
      "vol": "11,40"
    },
    {
      "name": "CSTB2107",
      "vol": "172,20"
    },
    {
      "name": "CSV",
      "vol": "16,60"
    },
    {
      "name": "CTCB2101",
      "vol": "1,70"
    },
    {
      "name": "CTCB2105",
      "vol": "1,60"
    },
    {
      "name": "CTCB2106",
      "vol": "165,00"
    },
    {
      "name": "CTCH2101",
      "vol": ""
    },
    {
      "name": "CTD",
      "vol": "20,20"
    },
    {
      "name": "CTF",
      "vol": "58,00"
    },
    {
      "name": "CTG",
      "vol": "1,134,70"
    },
    {
      "name": "CTI",
      "vol": "139,20"
    },
    {
      "name": "CTS",
      "vol": "134,10"
    },
    {
      "name": "CVHM2101",
      "vol": "4,70"
    },
    {
      "name": "CVHM2107",
      "vol": "50,80"
    },
    {
      "name": "CVIC2101",
      "vol": "10"
    },
    {
      "name": "CVIC2103",
      "vol": "110,70"
    },
    {
      "name": "CVIC2104",
      "vol": "7,20"
    },
    {
      "name": "CVIC2105",
      "vol": "254,40"
    },
    {
      "name": "CVJC2101",
      "vol": "20,20"
    },
    {
      "name": "CVJC2102",
      "vol": ""
    },
    {
      "name": "CVNM2101",
      "vol": ""
    },
    {
      "name": "CVNM2104",
      "vol": "73,90"
    },
    {
      "name": "CVNM2105",
      "vol": "195,20"
    },
    {
      "name": "CVNM2106",
      "vol": ""
    },
    {
      "name": "CVNM2107",
      "vol": "10"
    },
    {
      "name": "CVNM2108",
      "vol": "2,50"
    },
    {
      "name": "CVNM2109",
      "vol": "23,00"
    },
    {
      "name": "CVPB2105",
      "vol": "3,50"
    },
    {
      "name": "CVPB2106",
      "vol": "497,90"
    },
    {
      "name": "CVRE2101",
      "vol": "2,90"
    },
    {
      "name": "CVRE2105",
      "vol": "1,80"
    },
    {
      "name": "CVRE2106",
      "vol": "285,40"
    },
    {
      "name": "CVRE2107",
      "vol": "12,00"
    },
    {
      "name": "CVT",
      "vol": ""
    },
    {
      "name": "D2D",
      "vol": "11,40"
    },
    {
      "name": "DAG",
      "vol": "9,80"
    },
    {
      "name": "DAH",
      "vol": "27,50"
    },
    {
      "name": "DAT",
      "vol": "30"
    },
    {
      "name": "DBC",
      "vol": "248,30"
    },
    {
      "name": "DBD",
      "vol": "7,20"
    },
    {
      "name": "DBT",
      "vol": "10,60"
    },
    {
      "name": "DC4",
      "vol": "10,40"
    },
    {
      "name": "DCL",
      "vol": "74,30"
    },
    {
      "name": "DCM",
      "vol": "145,70"
    },
    {
      "name": "DGC",
      "vol": "33,00"
    },
    {
      "name": "DGW",
      "vol": "68,20"
    },
    {
      "name": "DHA",
      "vol": "18,30"
    },
    {
      "name": "DHC",
      "vol": "32,50"
    },
    {
      "name": "DHG",
      "vol": "3,60"
    },
    {
      "name": "DHM",
      "vol": "49,20"
    },
    {
      "name": "DIG",
      "vol": "629,80"
    },
    {
      "name": "DLG",
      "vol": "1,148,50"
    },
    {
      "name": "DMC",
      "vol": "2,20"
    },
    {
      "name": "DPG",
      "vol": "83,10"
    },
    {
      "name": "DPM",
      "vol": "331,80"
    },
    {
      "name": "DPR",
      "vol": "15,10"
    },
    {
      "name": "DQC",
      "vol": "16,20"
    },
    {
      "name": "DRC",
      "vol": "99,60"
    },
    {
      "name": "DRH",
      "vol": "138,20"
    },
    {
      "name": "DRL",
      "vol": ""
    },
    {
      "name": "DSN",
      "vol": "70"
    },
    {
      "name": "DTA",
      "vol": "21,30"
    },
    {
      "name": "DTL",
      "vol": "2,00"
    },
    {
      "name": "DTT",
      "vol": ""
    },
    {
      "name": "DVP",
      "vol": "11,80"
    },
    {
      "name": "DXG",
      "vol": "953,00"
    },
    {
      "name": "DXS",
      "vol": "12,50"
    },
    {
      "name": "DXV",
      "vol": ""
    },
    {
      "name": "E1VFVN30",
      "vol": "11,30"
    },
    {
      "name": "EIB",
      "vol": "38,40"
    },
    {
      "name": "ELC",
      "vol": "39,40"
    },
    {
      "name": "EMC",
      "vol": ""
    },
    {
      "name": "EVE",
      "vol": "9,00"
    },
    {
      "name": "EVG",
      "vol": "14,60"
    },
    {
      "name": "FCM",
      "vol": "6,50"
    },
    {
      "name": "FCN",
      "vol": "360,80"
    },
    {
      "name": "FDC",
      "vol": ""
    },
    {
      "name": "FIR",
      "vol": "62,70"
    },
    {
      "name": "FIT",
      "vol": "13,232,50"
    },
    {
      "name": "FLC",
      "vol": "1,468,10"
    },
    {
      "name": "FMC",
      "vol": "10,10"
    },
    {
      "name": "FPT",
      "vol": "235,20"
    },
    {
      "name": "FRT",
      "vol": "147,50"
    },
    {
      "name": "FTM",
      "vol": "47,20"
    },
    {
      "name": "FTS",
      "vol": "53,20"
    },
    {
      "name": "FUCTVGF2",
      "vol": ""
    },
    {
      "name": "FUCVREIT",
      "vol": "2,90"
    },
    {
      "name": "FUEMAV30",
      "vol": "30"
    },
    {
      "name": "FUESSV30",
      "vol": "9,10"
    },
    {
      "name": "FUESSV50",
      "vol": "25,00"
    },
    {
      "name": "FUESSVFL",
      "vol": "4,10"
    },
    {
      "name": "FUEVFVND",
      "vol": "25,10"
    },
    {
      "name": "FUEVN100",
      "vol": "10"
    },
    {
      "name": "GAB",
      "vol": "20"
    },
    {
      "name": "GAS",
      "vol": "68,90"
    },
    {
      "name": "GDT",
      "vol": "4,20"
    },
    {
      "name": "GEG",
      "vol": "63,90"
    },
    {
      "name": "GEX",
      "vol": "1,380,00"
    },
    {
      "name": "GIL",
      "vol": "22,40"
    },
    {
      "name": "GMC",
      "vol": "7,90"
    },
    {
      "name": "GMD",
      "vol": "274,70"
    },
    {
      "name": "GSP",
      "vol": "10,30"
    },
    {
      "name": "GTA",
      "vol": "1,60"
    },
    {
      "name": "GTN",
      "vol": "110,30"
    },
    {
      "name": "GVR",
      "vol": "453,80"
    },
    {
      "name": "HAG",
      "vol": "352,60"
    },
    {
      "name": "HAH",
      "vol": "142,30"
    },
    {
      "name": "HAI",
      "vol": "223,10"
    },
    {
      "name": "HAP",
      "vol": "28,40"
    },
    {
      "name": "HAR",
      "vol": "75,60"
    },
    {
      "name": "HAS",
      "vol": ""
    },
    {
      "name": "HAX",
      "vol": "61,50"
    },
    {
      "name": "HBC",
      "vol": "673,00"
    },
    {
      "name": "HCD",
      "vol": "261,40"
    },
    {
      "name": "HCM",
      "vol": "429,90"
    },
    {
      "name": "HDB",
      "vol": "212,10"
    },
    {
      "name": "HDC",
      "vol": "29,90"
    },
    {
      "name": "HDG",
      "vol": "168,80"
    },
    {
      "name": "HHP",
      "vol": "72,30"
    },
    {
      "name": "HHS",
      "vol": "279,30"
    },
    {
      "name": "HID",
      "vol": "124,00"
    },
    {
      "name": "HII",
      "vol": "231,70"
    },
    {
      "name": "HMC",
      "vol": "11,70"
    },
    {
      "name": "HNG",
      "vol": "676,10"
    },
    {
      "name": "HOT",
      "vol": ""
    },
    {
      "name": "HPG",
      "vol": "9,518,50"
    },
    {
      "name": "HPX",
      "vol": "154,70"
    },
    {
      "name": "HQC",
      "vol": "1,232,70"
    },
    {
      "name": "HRC",
      "vol": ""
    },
    {
      "name": "HSG",
      "vol": "3,369,90"
    },
    {
      "name": "HSL",
      "vol": "15,40"
    },
    {
      "name": "HT1",
      "vol": "192,80"
    },
    {
      "name": "HTI",
      "vol": "10,60"
    },
    {
      "name": "HTL",
      "vol": "3,30"
    },
    {
      "name": "HTN",
      "vol": "31,60"
    },
    {
      "name": "HTV",
      "vol": "50"
    },
    {
      "name": "HU1",
      "vol": "5,10"
    },
    {
      "name": "HU3",
      "vol": ""
    },
    {
      "name": "HUB",
      "vol": ""
    },
    {
      "name": "HVH",
      "vol": "62,00"
    },
    {
      "name": "HVN",
      "vol": "413,00"
    },
    {
      "name": "HVX",
      "vol": "117,20"
    },
    {
      "name": "IBC",
      "vol": "70,50"
    },
    {
      "name": "ICT",
      "vol": "2,70"
    },
    {
      "name": "IDI",
      "vol": "130,70"
    },
    {
      "name": "IJC",
      "vol": "447,80"
    },
    {
      "name": "ILB",
      "vol": "5,00"
    },
    {
      "name": "IMP",
      "vol": "10"
    },
    {
      "name": "ITA",
      "vol": "530,40"
    },
    {
      "name": "ITC",
      "vol": "23,70"
    },
    {
      "name": "ITD",
      "vol": "27,60"
    },
    {
      "name": "JVC",
      "vol": "4,424,00"
    },
    {
      "name": "KBC",
      "vol": "721,20"
    },
    {
      "name": "KDC",
      "vol": "337,30"
    },
    {
      "name": "KDH",
      "vol": "291,40"
    },
    {
      "name": "KHG",
      "vol": "70,70"
    },
    {
      "name": "KHP",
      "vol": "10,70"
    },
    {
      "name": "KMR",
      "vol": "78,60"
    },
    {
      "name": "KOS",
      "vol": "89,60"
    },
    {
      "name": "KPF",
      "vol": "141,40"
    },
    {
      "name": "KSB",
      "vol": "174,90"
    },
    {
      "name": "L10",
      "vol": ""
    },
    {
      "name": "LAF",
      "vol": "2,60"
    },
    {
      "name": "LBM",
      "vol": "40"
    },
    {
      "name": "LCG",
      "vol": "595,20"
    },
    {
      "name": "LCM",
      "vol": ""
    },
    {
      "name": "LDG",
      "vol": "519,90"
    },
    {
      "name": "LEC",
      "vol": "90"
    },
    {
      "name": "LGC",
      "vol": ""
    },
    {
      "name": "LGL",
      "vol": "11,50"
    },
    {
      "name": "LHG",
      "vol": "22,90"
    },
    {
      "name": "LIX",
      "vol": "1,40"
    },
    {
      "name": "LM8",
      "vol": "60"
    },
    {
      "name": "LPB",
      "vol": "331,20"
    },
    {
      "name": "LSS",
      "vol": "131,30"
    },
    {
      "name": "MBB",
      "vol": "1,562,40"
    },
    {
      "name": "MCG",
      "vol": "48,20"
    },
    {
      "name": "MCP",
      "vol": ""
    },
    {
      "name": "MDG",
      "vol": ""
    },
    {
      "name": "MHC",
      "vol": "250,00"
    },
    {
      "name": "MIG",
      "vol": "96,00"
    },
    {
      "name": "MSB",
      "vol": "354,40"
    },
    {
      "name": "MSH",
      "vol": "23,30"
    },
    {
      "name": "MSN",
      "vol": "99,30"
    },
    {
      "name": "MWG",
      "vol": "332,70"
    },
    {
      "name": "NAF",
      "vol": "48,10"
    },
    {
      "name": "NAV",
      "vol": "10"
    },
    {
      "name": "NBB",
      "vol": "20"
    },
    {
      "name": "NCT",
      "vol": ""
    },
    {
      "name": "NHA",
      "vol": "21,50"
    },
    {
      "name": "NHH",
      "vol": "121,10"
    },
    {
      "name": "NKG",
      "vol": "615,90"
    },
    {
      "name": "NLG",
      "vol": "195,20"
    },
    {
      "name": "NNC",
      "vol": "28,50"
    },
    {
      "name": "NSC",
      "vol": "20"
    },
    {
      "name": "NT2",
      "vol": "96,20"
    },
    {
      "name": "NTL",
      "vol": "131,10"
    },
    {
      "name": "NVL",
      "vol": "517,60"
    },
    {
      "name": "NVT",
      "vol": "20"
    },
    {
      "name": "OCB",
      "vol": "141,00"
    },
    {
      "name": "OGC",
      "vol": "101,60"
    },
    {
      "name": "OPC",
      "vol": ""
    },
    {
      "name": "PAC",
      "vol": ""
    },
    {
      "name": "PAN",
      "vol": "124,50"
    },
    {
      "name": "PC1",
      "vol": "169,30"
    },
    {
      "name": "PDN",
      "vol": ""
    },
    {
      "name": "PDR",
      "vol": "471,40"
    },
    {
      "name": "PET",
      "vol": "168,50"
    },
    {
      "name": "PGC",
      "vol": "23,40"
    },
    {
      "name": "PGD",
      "vol": "50"
    },
    {
      "name": "PGI",
      "vol": "2,50"
    },
    {
      "name": "PHC",
      "vol": "722,00"
    },
    {
      "name": "PHR",
      "vol": "44,20"
    },
    {
      "name": "PIT",
      "vol": "12,00"
    },
    {
      "name": "PJT",
      "vol": "50"
    },
    {
      "name": "PLP",
      "vol": "142,90"
    },
    {
      "name": "PLX",
      "vol": "40,20"
    },
    {
      "name": "PME",
      "vol": ""
    },
    {
      "name": "PMG",
      "vol": "40"
    },
    {
      "name": "PNC",
      "vol": "10"
    },
    {
      "name": "PNJ",
      "vol": "55,50"
    },
    {
      "name": "POM",
      "vol": "68,70"
    },
    {
      "name": "POW",
      "vol": "1,341,00"
    },
    {
      "name": "PPC",
      "vol": "29,70"
    },
    {
      "name": "PSH",
      "vol": "35,90"
    },
    {
      "name": "PTB",
      "vol": "4,90"
    },
    {
      "name": "PTC",
      "vol": "1,20"
    },
    {
      "name": "PTL",
      "vol": "1,20"
    },
    {
      "name": "PVD",
      "vol": "483,10"
    },
    {
      "name": "PVT",
      "vol": "947,20"
    },
    {
      "name": "PXI",
      "vol": "3,20"
    },
    {
      "name": "PXS",
      "vol": "12,00"
    },
    {
      "name": "QBS",
      "vol": "143,50"
    },
    {
      "name": "QCG",
      "vol": "13,40"
    },
    {
      "name": "RAL",
      "vol": "1,20"
    },
    {
      "name": "RDP",
      "vol": "72,30"
    },
    {
      "name": "REE",
      "vol": "159,20"
    },
    {
      "name": "RIC",
      "vol": ""
    },
    {
      "name": "ROS",
      "vol": "788,80"
    },
    {
      "name": "S4A",
      "vol": ""
    },
    {
      "name": "SAB",
      "vol": "7,10"
    },
    {
      "name": "SAM",
      "vol": "31,00"
    },
    {
      "name": "SAV",
      "vol": "12,90"
    },
    {
      "name": "SBA",
      "vol": "15,10"
    },
    {
      "name": "SBT",
      "vol": "462,60"
    },
    {
      "name": "SBV",
      "vol": "18,00"
    },
    {
      "name": "SC5",
      "vol": "2,10"
    },
    {
      "name": "SCD",
      "vol": ""
    },
    {
      "name": "SCR",
      "vol": "815,60"
    },
    {
      "name": "SCS",
      "vol": "1,40"
    },
    {
      "name": "SFC",
      "vol": ""
    },
    {
      "name": "SFG",
      "vol": "40"
    },
    {
      "name": "SFI",
      "vol": "1,00"
    },
    {
      "name": "SGN",
      "vol": "20"
    },
    {
      "name": "SGR",
      "vol": "9,30"
    },
    {
      "name": "SGT",
      "vol": "153,90"
    },
    {
      "name": "SHA",
      "vol": "16,50"
    },
    {
      "name": "SHI",
      "vol": "67,70"
    },
    {
      "name": "SHP",
      "vol": ""
    },
    {
      "name": "SII",
      "vol": ""
    },
    {
      "name": "SJD",
      "vol": "4,40"
    },
    {
      "name": "SJF",
      "vol": "3,242,60"
    },
    {
      "name": "SJS",
      "vol": "92,40"
    },
    {
      "name": "SKG",
      "vol": "49,60"
    },
    {
      "name": "SMA",
      "vol": "10"
    },
    {
      "name": "SMB",
      "vol": ""
    },
    {
      "name": "SMC",
      "vol": "155,50"
    },
    {
      "name": "SPM",
      "vol": "4,40"
    },
    {
      "name": "SRC",
      "vol": "1,20"
    },
    {
      "name": "SRF",
      "vol": "10,00"
    },
    {
      "name": "SSB",
      "vol": "203,60"
    },
    {
      "name": "SSC",
      "vol": "10"
    },
    {
      "name": "SSI",
      "vol": "7,338,80"
    },
    {
      "name": "ST8",
      "vol": ""
    },
    {
      "name": "STB",
      "vol": "1,860,50"
    },
    {
      "name": "STG",
      "vol": "20"
    },
    {
      "name": "STK",
      "vol": "3,10"
    },
    {
      "name": "SVC",
      "vol": ""
    },
    {
      "name": "SVD",
      "vol": "15,20"
    },
    {
      "name": "SVI",
      "vol": ""
    },
    {
      "name": "SVT",
      "vol": ""
    },
    {
      "name": "SZC",
      "vol": "69,40"
    },
    {
      "name": "SZL",
      "vol": "1,10"
    },
    {
      "name": "TAC",
      "vol": "10"
    },
    {
      "name": "TBC",
      "vol": "70"
    },
    {
      "name": "TCB",
      "vol": "843,40"
    },
    {
      "name": "TCD",
      "vol": "194,80"
    },
    {
      "name": "TCH",
      "vol": "2,163,20"
    },
    {
      "name": "TCL",
      "vol": "21,10"
    },
    {
      "name": "TCM",
      "vol": "213,90"
    },
    {
      "name": "TCO",
      "vol": "1,354,60"
    },
    {
      "name": "TCR",
      "vol": "10"
    },
    {
      "name": "TCT",
      "vol": "1,20"
    },
    {
      "name": "TDC",
      "vol": "205,60"
    },
    {
      "name": "TDG",
      "vol": "557,50"
    },
    {
      "name": "TDH",
      "vol": "255,60"
    },
    {
      "name": "TDM",
      "vol": "154,60"
    },
    {
      "name": "TDP",
      "vol": "9,30"
    },
    {
      "name": "TDW",
      "vol": ""
    },
    {
      "name": "TEG",
      "vol": "27,60"
    },
    {
      "name": "TGG",
      "vol": "28,10"
    },
    {
      "name": "THG",
      "vol": "50"
    },
    {
      "name": "THI",
      "vol": "1,10"
    },
    {
      "name": "TIP",
      "vol": "21,80"
    },
    {
      "name": "TIX",
      "vol": "1,10"
    },
    {
      "name": "TLD",
      "vol": "110,90"
    },
    {
      "name": "TLG",
      "vol": "13,70"
    },
    {
      "name": "TLH",
      "vol": "599,80"
    },
    {
      "name": "TMP",
      "vol": "10"
    },
    {
      "name": "TMS",
      "vol": "2,40"
    },
    {
      "name": "TMT",
      "vol": "2,10"
    },
    {
      "name": "TN1",
      "vol": "2,50"
    },
    {
      "name": "TNA",
      "vol": "35,10"
    },
    {
      "name": "TNC",
      "vol": ""
    },
    {
      "name": "TNH",
      "vol": "134,00"
    },
    {
      "name": "TNI",
      "vol": "33,70"
    },
    {
      "name": "TNT",
      "vol": "23,70"
    },
    {
      "name": "TPB",
      "vol": "583,40"
    },
    {
      "name": "TPC",
      "vol": ""
    },
    {
      "name": "TRA",
      "vol": "10"
    },
    {
      "name": "TRC",
      "vol": ""
    },
    {
      "name": "TS4",
      "vol": ""
    },
    {
      "name": "TSC",
      "vol": "345,40"
    },
    {
      "name": "TTA",
      "vol": "131,00"
    },
    {
      "name": "TTB",
      "vol": "310,70"
    },
    {
      "name": "TTE",
      "vol": ""
    },
    {
      "name": "TTF",
      "vol": "1,239,10"
    },
    {
      "name": "TV2",
      "vol": "21,90"
    },
    {
      "name": "TVB",
      "vol": "53,20"
    },
    {
      "name": "TVS",
      "vol": "6,80"
    },
    {
      "name": "TVT",
      "vol": ""
    },
    {
      "name": "TYA",
      "vol": "1,60"
    },
    {
      "name": "UDC",
      "vol": "2,30"
    },
    {
      "name": "UIC",
      "vol": "3,20"
    },
    {
      "name": "VAF",
      "vol": "20"
    },
    {
      "name": "VCA",
      "vol": "4,10"
    },
    {
      "name": "VCB",
      "vol": "84,10"
    },
    {
      "name": "VCF",
      "vol": ""
    },
    {
      "name": "VCG",
      "vol": "44,40"
    },
    {
      "name": "VCI",
      "vol": "637,70"
    },
    {
      "name": "VDP",
      "vol": "60"
    },
    {
      "name": "VDS",
      "vol": "103,70"
    },
    {
      "name": "VFG",
      "vol": "20"
    },
    {
      "name": "VGC",
      "vol": "333,40"
    },
    {
      "name": "VHC",
      "vol": "171,90"
    },
    {
      "name": "VHM",
      "vol": "802,10"
    },
    {
      "name": "VIB",
      "vol": "61,40"
    },
    {
      "name": "VIC",
      "vol": "333,30"
    },
    {
      "name": "VID",
      "vol": ""
    },
    {
      "name": "VIP",
      "vol": "58,00"
    },
    {
      "name": "VIS",
      "vol": "40"
    },
    {
      "name": "VIX",
      "vol": "6,614,10"
    },
    {
      "name": "VJC",
      "vol": "202,00"
    },
    {
      "name": "VMD",
      "vol": "2,30"
    },
    {
      "name": "VND",
      "vol": "595,60"
    },
    {
      "name": "VNE",
      "vol": "98,00"
    },
    {
      "name": "VNG",
      "vol": "12,60"
    },
    {
      "name": "VNL",
      "vol": "264,50"
    },
    {
      "name": "VNM",
      "vol": "209,40"
    },
    {
      "name": "VNS",
      "vol": ""
    },
    {
      "name": "VOS",
      "vol": "443,10"
    },
    {
      "name": "VPB",
      "vol": "598,10"
    },
    {
      "name": "VPD",
      "vol": "1,80"
    },
    {
      "name": "VPG",
      "vol": "140,30"
    },
    {
      "name": "VPH",
      "vol": "376,30"
    },
    {
      "name": "VPI",
      "vol": "182,60"
    },
    {
      "name": "VPS",
      "vol": "2,00"
    },
    {
      "name": "VRC",
      "vol": "8,00"
    },
    {
      "name": "VRE",
      "vol": "284,30"
    },
    {
      "name": "VSC",
      "vol": "12,30"
    },
    {
      "name": "VSH",
      "vol": "70"
    },
    {
      "name": "VSI",
      "vol": ""
    },
    {
      "name": "VTB",
      "vol": "1,30"
    },
    {
      "name": "VTO",
      "vol": "42,10"
    },
    {
      "name": "YBM",
      "vol": "1,90"
    },
    {
      "name": "YEG",
      "vol": "6,30"
    }
  ],
  "url": "https://iboard.ssi.com.vn/bang-gia/hose",
  "time": "9:39",
  "count": 4
}